{
"meta":{"test_sets":[],"test_metrics":[],"learn_metrics":[{"best_value":"Min","name":"Logloss"}],"launch_mode":"Train","parameters":"","iteration_count":150,"learn_sets":["learn"],"name":"experiment"},
"iterations":[
{"learn":[0.637910338],"iteration":0,"passed_time":0.002772476457,"remaining_time":0.4130989921},
{"learn":[0.5883679993],"iteration":1,"passed_time":0.004854655058,"remaining_time":0.3592444743},
{"learn":[0.5450076057],"iteration":2,"passed_time":0.006877063483,"remaining_time":0.3369761107},
{"learn":[0.5087283121],"iteration":3,"passed_time":0.01025152837,"remaining_time":0.3741807855},
{"learn":[0.4770491371],"iteration":4,"passed_time":0.01266029126,"remaining_time":0.3671484466},
{"learn":[0.4526809637],"iteration":5,"passed_time":0.0167335132,"remaining_time":0.4016043167},
{"learn":[0.4293185654],"iteration":6,"passed_time":0.0185539877,"remaining_time":0.379031463},
{"learn":[0.4086279231],"iteration":7,"passed_time":0.02117921789,"remaining_time":0.3759311175},
{"learn":[0.3918504254],"iteration":8,"passed_time":0.02351593807,"remaining_time":0.3684163631},
{"learn":[0.3784473472],"iteration":9,"passed_time":0.02578460805,"remaining_time":0.3609845127},
{"learn":[0.3639481237],"iteration":10,"passed_time":0.02825410362,"remaining_time":0.3570291276},
{"learn":[0.3513188472],"iteration":11,"passed_time":0.03216401841,"remaining_time":0.3698862117},
{"learn":[0.3418184227],"iteration":12,"passed_time":0.03480250614,"remaining_time":0.3667648724},
{"learn":[0.3319944834],"iteration":13,"passed_time":0.03714494967,"remaining_time":0.3608366539},
{"learn":[0.321893697],"iteration":14,"passed_time":0.03956399092,"remaining_time":0.3560759183},
{"learn":[0.3141552118],"iteration":15,"passed_time":0.0425032437,"remaining_time":0.355964666},
{"learn":[0.3093046425],"iteration":16,"passed_time":0.044765017,"remaining_time":0.3502204271},
{"learn":[0.3049753164],"iteration":17,"passed_time":0.04693091501,"remaining_time":0.3441600434},
{"learn":[0.299510108],"iteration":18,"passed_time":0.04919896999,"remaining_time":0.339213951},
{"learn":[0.29534335],"iteration":19,"passed_time":0.0512283551,"remaining_time":0.3329843082},
{"learn":[0.2889881836],"iteration":20,"passed_time":0.05443419033,"remaining_time":0.3343814549},
{"learn":[0.2840899125],"iteration":21,"passed_time":0.05680977062,"remaining_time":0.3305295745},
{"learn":[0.277882391],"iteration":22,"passed_time":0.05946167673,"remaining_time":0.3283318671},
{"learn":[0.274139862],"iteration":23,"passed_time":0.06292469354,"remaining_time":0.3303546411},
{"learn":[0.2703272888],"iteration":24,"passed_time":0.06699286463,"remaining_time":0.3349643231},
{"learn":[0.2678522282],"iteration":25,"passed_time":0.06918927106,"remaining_time":0.3299796004},
{"learn":[0.2651491451],"iteration":26,"passed_time":0.0720017418,"remaining_time":0.3280079349},
{"learn":[0.2617358916],"iteration":27,"passed_time":0.07443398643,"remaining_time":0.3243195123},
{"learn":[0.2589155647],"iteration":28,"passed_time":0.07901225234,"remaining_time":0.3296718115},
{"learn":[0.2559570794],"iteration":29,"passed_time":0.08090748956,"remaining_time":0.3236299583},
{"learn":[0.2519924045],"iteration":30,"passed_time":0.08312160855,"remaining_time":0.3190797231},
{"learn":[0.2506565966],"iteration":31,"passed_time":0.08494248472,"remaining_time":0.3132254124},
{"learn":[0.2490864515],"iteration":32,"passed_time":0.08808056725,"remaining_time":0.3122856475},
{"learn":[0.2472859857],"iteration":33,"passed_time":0.09046258839,"remaining_time":0.3086370663},
{"learn":[0.2450666508],"iteration":34,"passed_time":0.09280805777,"remaining_time":0.3049407612},
{"learn":[0.2410383117],"iteration":35,"passed_time":0.09550889568,"remaining_time":0.3024448363},
{"learn":[0.238815926],"iteration":36,"passed_time":0.0980635315,"remaining_time":0.2994913259},
{"learn":[0.2373037069],"iteration":37,"passed_time":0.1009693592,"remaining_time":0.2975939007},
{"learn":[0.2361800617],"iteration":38,"passed_time":0.1032247991,"remaining_time":0.293793659},
{"learn":[0.2331230127],"iteration":39,"passed_time":0.1059082245,"remaining_time":0.2912476173},
{"learn":[0.2301057846],"iteration":40,"passed_time":0.1080775767,"remaining_time":0.2873281916},
{"learn":[0.2291118019],"iteration":41,"passed_time":0.1112074533,"remaining_time":0.2859620229},
{"learn":[0.2274889162],"iteration":42,"passed_time":0.1139637356,"remaining_time":0.2835841792},
{"learn":[0.2260876876],"iteration":43,"passed_time":0.1160458267,"remaining_time":0.2795649461},
{"learn":[0.2246033086],"iteration":44,"passed_time":0.1187140745,"remaining_time":0.2769995072},
{"learn":[0.2212045568],"iteration":45,"passed_time":0.1233511689,"remaining_time":0.2788809037},
{"learn":[0.2150074982],"iteration":46,"passed_time":0.1265273674,"remaining_time":0.2772833796},
{"learn":[0.213448753],"iteration":47,"passed_time":0.1288072924,"remaining_time":0.2737154964},
{"learn":[0.2126783178],"iteration":48,"passed_time":0.1309164669,"remaining_time":0.2698482277},
{"learn":[0.2113537226],"iteration":49,"passed_time":0.1345678735,"remaining_time":0.2691357469},
{"learn":[0.2103244536],"iteration":50,"passed_time":0.136815715,"remaining_time":0.2655834468},
{"learn":[0.2095477635],"iteration":51,"passed_time":0.1391010401,"remaining_time":0.2621519601},
{"learn":[0.2078842407],"iteration":52,"passed_time":0.1415982949,"remaining_time":0.2591515963},
{"learn":[0.2071855082],"iteration":53,"passed_time":0.1448967662,"remaining_time":0.2575942511},
{"learn":[0.2056182599],"iteration":54,"passed_time":0.1474833413,"remaining_time":0.2547439532},
{"learn":[0.2046444698],"iteration":55,"passed_time":0.1498246432,"remaining_time":0.2514913653},
{"learn":[0.2034411728],"iteration":56,"passed_time":0.1520539572,"remaining_time":0.2480880354},
{"learn":[0.2003730939],"iteration":57,"passed_time":0.153806194,"remaining_time":0.2439684456},
{"learn":[0.1990240843],"iteration":58,"passed_time":0.1565516104,"remaining_time":0.2414609584},
{"learn":[0.1979371133],"iteration":59,"passed_time":0.1586865,"remaining_time":0.2380297499},
{"learn":[0.1971587301],"iteration":60,"passed_time":0.1694721557,"remaining_time":0.2472626534},
{"learn":[0.1953085061],"iteration":61,"passed_time":0.1720642167,"remaining_time":0.2442201785},
{"learn":[0.1940940096],"iteration":62,"passed_time":0.1752449635,"remaining_time":0.2420049496},
{"learn":[0.1933471203],"iteration":63,"passed_time":0.1774896492,"remaining_time":0.2385017161},
{"learn":[0.19222814],"iteration":64,"passed_time":0.1797822134,"remaining_time":0.2350998176},
{"learn":[0.1914354607],"iteration":65,"passed_time":0.1821052936,"remaining_time":0.2317703736},
{"learn":[0.1906097215],"iteration":66,"passed_time":0.1838572629,"remaining_time":0.2277634749},
{"learn":[0.1899578809],"iteration":67,"passed_time":0.1868230474,"remaining_time":0.225286616},
{"learn":[0.1892108731],"iteration":68,"passed_time":0.1890685856,"remaining_time":0.2219500788},
{"learn":[0.1878717312],"iteration":69,"passed_time":0.1911588534,"remaining_time":0.2184672611},
{"learn":[0.1869160772],"iteration":70,"passed_time":0.1945045049,"remaining_time":0.2164205055},
{"learn":[0.1826845904],"iteration":71,"passed_time":0.1975164037,"remaining_time":0.213976104},
{"learn":[0.1793252356],"iteration":72,"passed_time":0.1999341333,"remaining_time":0.2108894283},
{"learn":[0.1787778969],"iteration":73,"passed_time":0.2021145364,"remaining_time":0.2075770914},
{"learn":[0.1779763195],"iteration":74,"passed_time":0.2042902411,"remaining_time":0.2042902411},
{"learn":[0.1763884491],"iteration":75,"passed_time":0.2071377728,"remaining_time":0.2016867787},
{"learn":[0.1748930573],"iteration":76,"passed_time":0.2112233439,"remaining_time":0.2002507027},
{"learn":[0.1740137675],"iteration":77,"passed_time":0.2137515421,"remaining_time":0.1973091158},
{"learn":[0.1735718686],"iteration":78,"passed_time":0.2160741323,"remaining_time":0.1941932075},
{"learn":[0.1730195704],"iteration":79,"passed_time":0.2188173811,"remaining_time":0.1914652085},
{"learn":[0.1722697226],"iteration":80,"passed_time":0.2212166032,"remaining_time":0.1884437731},
{"learn":[0.1716948705],"iteration":81,"passed_time":0.22552903,"remaining_time":0.1870240736},
{"learn":[0.1713580776],"iteration":82,"passed_time":0.2279111695,"remaining_time":0.1839764862},
{"learn":[0.1708058657],"iteration":83,"passed_time":0.2307407102,"remaining_time":0.1812962723},
{"learn":[0.1700667268],"iteration":84,"passed_time":0.2330328253,"remaining_time":0.1782015723},
{"learn":[0.1684542456],"iteration":85,"passed_time":0.235668548,"remaining_time":0.175381245},
{"learn":[0.1676069967],"iteration":86,"passed_time":0.2377582066,"remaining_time":0.1721697358},
{"learn":[0.1650689413],"iteration":87,"passed_time":0.240263404,"remaining_time":0.1692764892},
{"learn":[0.1645293739],"iteration":88,"passed_time":0.2424332378,"remaining_time":0.1661621068},
{"learn":[0.1637461948],"iteration":89,"passed_time":0.2448041473,"remaining_time":0.1632027649},
{"learn":[0.1630513726],"iteration":90,"passed_time":0.2473042638,"remaining_time":0.1603401271},
{"learn":[0.1623392171],"iteration":91,"passed_time":0.2497468368,"remaining_time":0.1574490927},
{"learn":[0.1610680121],"iteration":92,"passed_time":0.2521906798,"remaining_time":0.1545684811},
{"learn":[0.160503185],"iteration":93,"passed_time":0.2545111357,"remaining_time":0.1516236553},
{"learn":[0.1585586308],"iteration":94,"passed_time":0.2603690646,"remaining_time":0.1507399847},
{"learn":[0.1577993814],"iteration":95,"passed_time":0.2645398201,"remaining_time":0.1488036488},
{"learn":[0.157441523],"iteration":96,"passed_time":0.266893192,"remaining_time":0.1458282389},
{"learn":[0.1563607196],"iteration":97,"passed_time":0.2693509017,"remaining_time":0.1429208866},
{"learn":[0.1546797528],"iteration":98,"passed_time":0.2717756597,"remaining_time":0.1400056429},
{"learn":[0.1541136708],"iteration":99,"passed_time":0.2750331134,"remaining_time":0.1375165567},
{"learn":[0.1535927411],"iteration":100,"passed_time":0.2774329887,"remaining_time":0.1345962025},
{"learn":[0.1529213992],"iteration":101,"passed_time":0.2798438191,"remaining_time":0.131691209},
{"learn":[0.1526386393],"iteration":102,"passed_time":0.2821967494,"remaining_time":0.1287693905},
{"learn":[0.1517801004],"iteration":103,"passed_time":0.2858514542,"remaining_time":0.1264342971},
{"learn":[0.1513744822],"iteration":104,"passed_time":0.291050992,"remaining_time":0.1247361394},
{"learn":[0.1508982126],"iteration":105,"passed_time":0.2949006182,"remaining_time":0.1224115774},
{"learn":[0.1504866472],"iteration":106,"passed_time":0.2969426351,"remaining_time":0.119332087},
{"learn":[0.1501885841],"iteration":107,"passed_time":0.299668403,"remaining_time":0.1165377123},
{"learn":[0.1495909549],"iteration":108,"passed_time":0.3019937032,"remaining_time":0.1135939618},
{"learn":[0.1490440332],"iteration":109,"passed_time":0.3043920669,"remaining_time":0.1106880243},
{"learn":[0.1476909403],"iteration":110,"passed_time":0.3067486105,"remaining_time":0.1077765388},
{"learn":[0.1475002372],"iteration":111,"passed_time":0.3091270583,"remaining_time":0.1048823948},
{"learn":[0.1463747252],"iteration":112,"passed_time":0.311480511,"remaining_time":0.1019891939},
{"learn":[0.1459437668],"iteration":113,"passed_time":0.3139925975,"remaining_time":0.09915555711},
{"learn":[0.1450596007],"iteration":114,"passed_time":0.3164892857,"remaining_time":0.09632282607},
{"learn":[0.1446813918],"iteration":115,"passed_time":0.3191825902,"remaining_time":0.09355351782},
{"learn":[0.1440491178],"iteration":116,"passed_time":0.3214030251,"remaining_time":0.09065213527},
{"learn":[0.1436156926],"iteration":117,"passed_time":0.3241096463,"remaining_time":0.08789414138},
{"learn":[0.1432398689],"iteration":118,"passed_time":0.3265045058,"remaining_time":0.08505579564},
{"learn":[0.1427870662],"iteration":119,"passed_time":0.3286384188,"remaining_time":0.08215960469},
{"learn":[0.1419003281],"iteration":120,"passed_time":0.3309038721,"remaining_time":0.07930753959},
{"learn":[0.1416386641],"iteration":121,"passed_time":0.3329234855,"remaining_time":0.0764086688},
{"learn":[0.1414144756],"iteration":122,"passed_time":0.3352034205,"remaining_time":0.07358123865},
{"learn":[0.1411510545],"iteration":123,"passed_time":0.3381236357,"remaining_time":0.07089689136},
{"learn":[0.1407343767],"iteration":124,"passed_time":0.3405886638,"remaining_time":0.06811773276},
{"learn":[0.1403079797],"iteration":125,"passed_time":0.3427434251,"remaining_time":0.06528446192},
{"learn":[0.1399920454],"iteration":126,"passed_time":0.344763071,"remaining_time":0.06243740656},
{"learn":[0.1396518255],"iteration":127,"passed_time":0.346514552,"remaining_time":0.05955718862},
{"learn":[0.1392903236],"iteration":128,"passed_time":0.3481553034,"remaining_time":0.05667644475},
{"learn":[0.1385963704],"iteration":129,"passed_time":0.3503535466,"remaining_time":0.05390054562},
{"learn":[0.1381199469],"iteration":130,"passed_time":0.3527802712,"remaining_time":0.05116660421},
{"learn":[0.1372379281],"iteration":131,"passed_time":0.3549150324,"remaining_time":0.04839750442},
{"learn":[0.1370423799],"iteration":132,"passed_time":0.3565103604,"remaining_time":0.04556899344},
{"learn":[0.1360803386],"iteration":133,"passed_time":0.3584211002,"remaining_time":0.04279654928},
{"learn":[0.1346370273],"iteration":134,"passed_time":0.3603165849,"remaining_time":0.0400351761},
{"learn":[0.1343943171],"iteration":135,"passed_time":0.3619938907,"remaining_time":0.03726407698},
{"learn":[0.1339505915],"iteration":136,"passed_time":0.3636992348,"remaining_time":0.03451160622},
{"learn":[0.1334671409],"iteration":137,"passed_time":0.3655237835,"remaining_time":0.03178467683},
{"learn":[0.1326516034],"iteration":138,"passed_time":0.3676445589,"remaining_time":0.02909417372},
{"learn":[0.1323555093],"iteration":139,"passed_time":0.36945671,"remaining_time":0.026389765},
{"learn":[0.1319655741],"iteration":140,"passed_time":0.3711366333,"remaining_time":0.02368957234},
{"learn":[0.131653615],"iteration":141,"passed_time":0.3726878028,"remaining_time":0.02099649593},
{"learn":[0.1312045134],"iteration":142,"passed_time":0.3742494666,"remaining_time":0.01831990396},
{"learn":[0.1308847992],"iteration":143,"passed_time":0.3758095728,"remaining_time":0.0156587322},
{"learn":[0.1303676116],"iteration":144,"passed_time":0.3775082936,"remaining_time":0.01301752737},
{"learn":[0.1297952707],"iteration":145,"passed_time":0.3790402156,"remaining_time":0.01038466344},
{"learn":[0.1289482542],"iteration":146,"passed_time":0.3805457559,"remaining_time":0.007766239915},
{"learn":[0.1285209443],"iteration":147,"passed_time":0.3820507328,"remaining_time":0.00516284774},
{"learn":[0.128341384],"iteration":148,"passed_time":0.3835131254,"remaining_time":0.002573913593},
{"learn":[0.1281586875],"iteration":149,"passed_time":0.3876955918,"remaining_time":0}
]}e":0}
]}